Week 13 Assignment/Code/binary.v
module binary (
    input  w,
    input  clk,
    input  reset,
    output reg z,
    output [2:0] state_out
);


    localparam A = 3'd0;
    localparam B = 3'd1;
    localparam C = 3'd2;
    localparam D = 3'd3;
    localparam E = 3'd4;

    reg [2:0] state;
    reg [2:0] next;

    assign state_out = state;

    always @(*) begin
        case (state)
            A: next = (w) ? D : B;
            B: next = (w) ? D : C;
            C: next = (w) ? D : C;
            D: next = (w) ? E : B;
            E: next = (w) ? E : B;
            default: next = A;
        endcase
    end

    always @(*) begin
        case (state)
            C: z = 1'b1;
            E: z = 1'b1;
            default: z = 1'b0;
        endcase
    end

    always @(posedge clk or posedge reset) begin
        if (reset)
            state <= A;
        else
            state <= next;
    end

endmodule

Week 13 Assignment/Code/dff.v
module dff(
    input  Default,
    input  D,
    input  clk,
    input  reset,
    output reg Q
);

    initial Q = Default;

    always @(posedge clk or posedge reset) begin
        if (reset)
            Q <= Default;
        else
            Q <= D;  
    end
endmodule

Week 13 Assignment/Code/onehot.v
module onehot (
    input w,     
    input clk,   
    input reset, 
    output z,    
    output [4:0] state_out 
);

    // --- Next State Wires ---
    wire Anext, Bnext, Cnext, Dnext, Enext;

    // --- Current State Wires ---
    wire Astate, Bstate, Cstate, Dstate, Estate;

    // Output the states to the LEDs (Order: E, D, C, B, A)
    assign state_out = {Estate, Dstate, Cstate, Bstate, Astate};
    
    // --- State Storage (dff Instantiation) ---

    dff dff_A ( .Default(1'b1), .D(Anext), .clk(clk), .reset(reset), .Q(Astate) );
    dff dff_B ( .Default(1'b0), .D(Bnext), .clk(clk), .reset(reset), .Q(Bstate) );
    dff dff_C ( .Default(1'b0), .D(Cnext), .clk(clk), .reset(reset), .Q(Cstate) );
    dff dff_D ( .Default(1'b0), .D(Dnext), .clk(clk), .reset(reset), .Q(Dstate) );
    dff dff_E ( .Default(1'b0), .D(Enext), .clk(clk), .reset(reset), .Q(Estate) );


    // --- Next State Logic (Combinational Assignments) ---
    assign Anext = 1'b0;
    assign Bnext = (~w) & (Astate | Dstate | Estate);
    assign Cnext = (~w) & (Bstate | Cstate);
    assign Dnext = w & (Astate | Bstate | Cstate);
    assign Enext = w & (Dstate | Estate);


    // --- Output Logic (Combinational - Moore Machine) ---
    assign z = Cstate | Estate;

endmodule

Week 13 Assignment/Code/top.v
module top(
    input [0:0] sw,     
    output [9:0] led, 
    input btnC,   
    input btnU    
);


    wire w_in = sw[0];
    
    wire clk = btnC;
    wire reset_in = btnU;

    wire z_oh; 
    wire z_bin; 
    wire [4:0] state_oh; 
    wire [2:0] state_bin; 

    onehot one_hot_inst (
        .w(w_in),
        .clk(clk), 
        .reset(reset_in),
        .z(z_oh),
        .state_out(state_oh)
    );

    binary binary_inst (
        .w(w_in),
        .clk(clk), 
        .reset(reset_in),
        .z(z_bin),
        .state_out(state_bin)
    );


    assign led[0] = z_oh;

    assign led[1] = z_bin;

    assign led[6:2] = state_oh;

    assign led[9:7] = state_bin;

endmodule

Week 13 Assignment/Code/test.v
module test();

    reg w;
    reg clk;
    reg reset;
    wire z_onehot;
    wire z_binary;
    wire [4:0] onehot_actual;
    wire [2:0] binary_actual;

    top uut(
        .sw(w),
        .btnC(clk),
        .btnU(reset),
        .led({binary_actual, onehot_actual, z_binary, z_onehot})
    );

    task automatic toggle_clock;
        begin
            #1 clk = 1;
            #1 clk = 0;
        end
    endtask
	
	    task automatic check_state_oh(input [2:0] expected_state, input expected_z);
        begin
            if (z_onehot !== expected_z) begin
                $display("FAILED OneHot Check. Expected output %b, found %b", expected_z, z_onehot);
                $finish;
            end
            if (1 << expected_state !== onehot_actual) begin
                $display("FAILED OneHot Check. Expected state %b, found %b", 1 << expected_state, onehot_actual);
                $finish;
            end
        end
    endtask

    task automatic check_state_bn(input [2:0] expected_state, input expected_z);
        begin
            if (z_binary !== expected_z) begin
                $display("FAILED Binary Check. Expected output %b, found %b", expected_z, z_binary);
                $finish;
            end
            if (expected_state !== binary_actual) begin
                $display("FAILED Binary Check. Expected state %b, found %b", expected_state, binary_actual);
                $finish;
            end
        end
    endtask

    task automatic check_state(input [2:0] expected_state, input expected_z);
        begin
            check_state_oh(expected_state, expected_z);
            check_state_bn(expected_state, expected_z);
        end
    endtask

    task automatic do_reset;
        begin
            clk = 0;
            w = 0;
            #1 reset = 1;
            #1 reset = 0;
        end
    endtask

    task automatic next_state(input nextw);
        begin
            w = nextw;
            toggle_clock;
        end
    endtask

    initial begin
        $dumpvars(0,test);

        do_reset;
        check_state('b000, 'b0);

        next_state('b0);
        check_state('b001, 'b0);

        next_state('b0);
        check_state('b010, 'b1);

        next_state('b0);
        check_state('b010, 'b1);

        next_state('b1);
        check_state('b011, 'b0);

        next_state('b1);
        check_state('b100, 'b1);

        next_state('b1);
        check_state('b100, 'b1);

        next_state('b0);
        check_state('b001, 'b0);

        next_state('b1);
        check_state('b011, 'b0);

        next_state('b0);
        check_state('b001, 'b0);

        do_reset;

        next_state('b1);
        check_state('b011, 'b0);

	$display("Test passed!");
	$finish;
    end

endmodule

Week 13 Assignment/project_1/project_1.sim/sim_1/behav/xsim/dump.vcd
$date
   Sun Nov 23 01:28:10 2025
$end

$version
  2025.1.0
$end

$timescale
  1ps
$end

$scope module test $end
$var reg 1 ! w $end
$var reg 1 " clk $end
$var reg 1 # reset $end
$var wire 1 $ z_onehot $end
$var wire 1 % z_binary $end
$var wire 5 & onehot_actual [4:0] $end
$var wire 3 ' binary_actual [2:0] $end
$scope module uut $end
$var wire 1 ( sw [0:0] $end
$var wire 10 ) led [9:0] $end
$var wire 1 * btnC $end
$var wire 1 + btnU $end
$var wire 1 , w_in $end
$var wire 1 - clk $end
$var wire 1 . reset_in $end
$var wire 1 / z_oh $end
$var wire 1 0 z_bin $end
$var wire 5 1 state_oh [4:0] $end
$var wire 3 2 state_bin [2:0] $end
$scope module one_hot_inst $end
$var wire 1 , w $end
$var wire 1 - clk $end
$var wire 1 . reset $end
$var wire 1 / z $end
$var wire 5 1 state_out [4:0] $end
$var wire 1 3 Anext $end
$var wire 1 4 Bnext $end
$var wire 1 5 Cnext $end
$var wire 1 6 Dnext $end
$var wire 1 7 Enext $end
$var wire 1 8 Astate $end
$var wire 1 9 Bstate $end
$var wire 1 : Cstate $end
$var wire 1 ; Dstate $end
$var wire 1 < Estate $end
$scope module dff_A $end
$var wire 1 = Default $end
$var wire 1 3 D $end
$var wire 1 - clk $end
$var wire 1 . reset $end
$var reg 1 > Q $end
$upscope $end
$scope module dff_B $end
$var wire 1 ? Default $end
$var wire 1 4 D $end
$var wire 1 - clk $end
$var wire 1 . reset $end
$var reg 1 @ Q $end
$upscope $end
$scope module dff_C $end
$var wire 1 A Default $end
$var wire 1 5 D $end
$var wire 1 - clk $end
$var wire 1 . reset $end
$var reg 1 B Q $end
$upscope $end
$scope module dff_D $end
$var wire 1 C Default $end
$var wire 1 6 D $end
$var wire 1 - clk $end
$var wire 1 . reset $end
$var reg 1 D Q $end
$upscope $end
$scope module dff_E $end
$var wire 1 E Default $end
$var wire 1 7 D $end
$var wire 1 - clk $end
$var wire 1 . reset $end
$var reg 1 F Q $end
$upscope $end
$upscope $end
$scope module binary_inst $end
$var wire 1 , w $end
$var wire 1 - clk $end
$var wire 1 . reset $end
$var reg 1 G z $end
$var wire 3 2 state_out [2:0] $end
$var reg 3 H state [2:0] $end
$var reg 3 I next [2:0] $end
$upscope $end
$upscope $end
$scope task toggle_clock $end
$upscope $end
$scope task check_state_oh $end
$upscope $end
$scope task check_state_bn $end
$upscope $end
$scope task check_state $end
$upscope $end
$scope task do_reset $end
$upscope $end
$scope task next_state $end
$upscope $end
$upscope $end
$enddefinitions $end

#0
$dumpvars
0!
0"
x#
0$
x%
b1 &
bx '
0(
bx00001x0 )
0*
x+
0,
0-
x.
0/
x0
b1 1
bx 2
03
14
05
06
07
18
09
0:
0;
0<
1=
1>
0?
0@
0A
0B
0C
0D
0E
0F
xG
bx H
b0 I
$end

#1000
1#
0%
b0 '
b100 )
1+
1.
00
b0 2
0G
b0 H
b1 I

#2000
0#
0+
0.

#3000
1"
b10 &
b1 '
b10001000 )
1*
1-
b10 1
b1 2
04
15
08
19
0>
1@
b1 H
b10 I

#4000
0"
0*
0-

#5000
1"
1$
1%
b100 &
b10 '
b100010011 )
1*
1-
1/
10
b100 1
b10 2
09
1:
0@
1B
1G
b10 H

#6000
0"
0*
0-

#7000
1"
1*
1-

#8000
1!
0"
1(
0*
1,
0-
05
16
b11 I

#9000
1"
0$
0%
b1000 &
b11 '
b110100000 )
1*
1-
0/
00
b1000 1
b11 2
06
17
0:
1;
0B
1D
0G
b11 H
b100 I

#10000
0"
0*
0-

#11000
1"
1$
1%
b10000 &
b100 '
b1001000011 )
1*
1-
1/
10
b10000 1
b100 2
0;
1<
0D
1F
1G
b100 H

#12000
0"
0*
0-

#13000
1"
1*
1-

#14000
0!
0"
0(
0*
0,
0-
14
07
b1 I

#15000
1"
0$
0%
b10 &
b1 '
b10001000 )
1*
1-
0/
00
b10 1
b1 2
04
15
19
0<
1@
0F
0G
b1 H
b10 I

#16000
1!
0"
1(
0*
1,
0-
05
16
b11 I

#17000
1"
b1000 &
b11 '
b110100000 )
1*
1-
b1000 1
b11 2
06
17
09
1;
0@
1D
b11 H
b100 I

#18000
0!
0"
0(
0*
0,
0-
14
07
b1 I

#19000
1"
b10 &
b1 '
b10001000 )
1*
1-
b10 1
b1 2
04
15
19
0;
1@
0D
b1 H
b10 I

#20000
0"
0*
0-

#21000
1#
b1 &
b0 '
b100 )
1+
1.
b1 1
b0 2
14
05
18
09
1>
0@
b0 H
b1 I

#22000
1!
0#
1(
0+
1,
0.
04
16
b11 I

#23000
1"
b1000 &
b11 '
b110100000 )
1*
1-
b1000 1
b11 2
06
17
08
1;
0>
1D
b11 H
b100 I

